fez/Anchors.py
fez/Arabic.py
fez/AvoidCollision.py
fez/BariYe.py
fez/Chain.py
fez/ClassDefinition.py
fez/Conditional.py
fez/CopyAnchors.py
fez/Debug.py
fez/Delete.py
fez/Feature.py
fez/FontEngineering.py
fez/ForLoop.py
fez/Fractions.py
fez/IMatra.py
fez/IfCollides.py
fez/Include.py
fez/KernToDistance.py
fez/Kerning.py
fez/LigatureFinder.py
fez/LoadPlugin.py
fez/MedialRa.py
fez/Position.py
fez/Routine.py
fez/Substitute.py
fez/Swap.py
fez/Variables.py
fez/__init__.py
fez/util.py
fez_language-1.4.0.data/scripts/fez2fea
fez_language-1.4.0.data/scripts/mergefez
fez_language-1.4.0.dist-info/AUTHORS.txt
fez_language-1.4.0.dist-info/LICENSE
fez_language-1.4.0.dist-info/METADATA
fez_language-1.4.0.dist-info/WHEEL
fez_language-1.4.0.dist-info/top_level.txt
fez_language-1.4.0.dist-info/RECORD
