Metadata-Version: 2.1
Name: fez-language
Version: 1.4.0
Summary: The FEZ language: Font Engineering made eaZy
Home-page: https://github.com/simoncozens/fez
Author: Simon Cozens
Author-email: simon@simon-cozens.org
License: MIT
Classifier: Programming Language :: Python
Classifier: Programming Language :: Python :: 2
Classifier: Programming Language :: Python :: 3
Classifier: License :: OSI Approved :: MIT License
Classifier: Development Status :: 4 - Beta
License-File: LICENSE
License-File: AUTHORS.txt
Requires-Dist: glyphtools (>=0.7.0)
Requires-Dist: fontTools
Requires-Dist: beziers (>=0.1.0)
Requires-Dist: lark
Requires-Dist: more-itertools
Requires-Dist: babelfont (>=3.0.0a7)
Requires-Dist: fontfeatures (>=1.3.0)
